geoshiny/__init__.py
geoshiny/__main__.py
geoshiny/database_extract.py
geoshiny/draw_helpers.py
geoshiny/import_hell.py
geoshiny/types.py
geoshiny-0.0.3.dist-info/METADATA
geoshiny-0.0.3.dist-info/WHEEL
geoshiny-0.0.3.dist-info/top_level.txt
geoshiny-0.0.3.dist-info/RECORD
