Metadata-Version: 2.1
Name: geoshiny
Version: 0.0.3
Summary: GIS data renderer
Home-page: https://github.com/jacopofar/geoshiny
Author: Jacopo Farina
Author-email: jacopo1.farina@gmail.com
License: MIT
Platform: UNKNOWN
Requires-Python: >=3.8
Requires-Dist: matplotlib
Requires-Dist: numpy
Requires-Dist: asyncpg
Requires-Dist: pyproj
Requires-Dist: Shapely
Provides-Extra: geotiff
Requires-Dist: GDAL ; extra == 'geotiff'
Provides-Extra: tests
Requires-Dist: pytest ; extra == 'tests'
Requires-Dist: pytest-asyncio ; extra == 'tests'
Requires-Dist: pytest-cov ; extra == 'tests'
Requires-Dist: flake8 ; extra == 'tests'
Requires-Dist: mypy ; extra == 'tests'
